LICENSE
MANIFEST.in
README.md
setup.cfg
setup.py
lxdatacleaner/__init__.py
lxdatacleaner/check.py
lxdatacleaner/clean.py
lxdatacleaner/domain.py
lxdatacleaner/flow.py
lxdatacleaner/input.py
lxdatacleaner/output.py
lxkjdatacleaner.egg-info/PKG-INFO
lxkjdatacleaner.egg-info/SOURCES.txt
lxkjdatacleaner.egg-info/dependency_links.txt
lxkjdatacleaner.egg-info/top_level.txt
test/test.py