Metadata-Version: 2.1
Name: lxkjdatacleaner
Version: 0.0.5
Summary: a library for data clean
Home-page: https://github.com/qihao123/lxdatacleaner
Author: Hao Qi
Author-email: 1047355811@qq.com
License: MIT License
Keywords: dataclean
Platform: any
